<T3DataStructure>
    	<meta>
		<langDisable>1</langDisable>
	</meta>
	<sheets>
                <schulung>
                        <ROOT>
                                <TCEforms>
                                        <sheetTitle>LLL:EXT:schulungen/locallang.xml:schulung</sheetTitle>
                                </TCEforms>
                                <type>array</type>
                                <el>
                                        <formwahl>
                                                <TCEforms>
                                                        <label>Darstellung</label>
                                                        <config>
                                                                <type>select</type>
                                                                <items type="array">
                                                                        <numIndex index="0" type="array">
                                                                                <numIndex index="0">Listenansicht</numIndex>
                                                                                <numIndex index="1">listView</numIndex>
                                                                        </numIndex>
                                                                        <numIndex index="1" type="array">
                                                                                <numIndex index="0">Detailansicht</numIndex>
                                                                                <numIndex index="1">detailView</numIndex>
                                                                        </numIndex>
                                                                </items>
                                                                <maxitems>1</maxitems>
                                                                <size>1</size>
                                                        </config>
                                                </TCEforms>
                                        </formwahl>
                                </el>
                        </ROOT>
                </schulung>
        </sheets>
</T3DataStructure>